lightweb/__init__.py
lightweb/web.py
lightweb-0.0.1.dist-info/LICENSE
lightweb-0.0.1.dist-info/METADATA
lightweb-0.0.1.dist-info/WHEEL
lightweb-0.0.1.dist-info/top_level.txt
lightweb-0.0.1.dist-info/RECORD
