Metadata-Version: 2.1
Name: lightweb
Version: 0.0.1
Summary: Light Web Utility for Django
Home-page: https://github.com/ni-ning/lightweb
Author: ni-ning
Author-email: nining1314@gmail.com
License: UNKNOWN
Keywords: Django,Request,Response
Platform: UNKNOWN
Classifier: Development Status :: 3 - Alpha
Classifier: Intended Audience :: Developers
Classifier: License :: OSI Approved :: MIT License
Classifier: Programming Language :: Python :: 3.4
Classifier: Programming Language :: Python :: 3.5
Classifier: Programming Language :: Python :: 3.6
Classifier: Programming Language :: Python :: 3.7
Requires-Dist: six
